my_first_ph3_package/__init__.py
my_first_ph3_package/cli.py
my_first_ph3_package/my_first_ph3_package.py
my_first_ph3_package/sub_package_1/__init__.py
my_first_ph3_package/sub_package_1/my_class_1.py
my_first_ph3_package/sub_package_2/__init__.py
my_first_ph3_package/sub_package_2/my_class_2.py
my_first_ph3_package/sub_package_2/my_class_3.py
my_first_ph3_package-0.2.0.dist-info/LICENSE
my_first_ph3_package-0.2.0.dist-info/METADATA
my_first_ph3_package-0.2.0.dist-info/WHEEL
my_first_ph3_package-0.2.0.dist-info/entry_points.txt
my_first_ph3_package-0.2.0.dist-info/RECORD
