Metadata-Version: 2.1
Name: my-first-ph3-package
Version: 0.2.0
Summary: PH3 packages are quick to make!
Home-page: https://github.com/my_first_ph3_package/my-first-ph3-package
Author: Fabien Mathieu
Author-email: fabien.mathieu@normalesup.org
Requires-Python: >=3.9,<4.0
Classifier: Programming Language :: Python :: 3
Classifier: Programming Language :: Python :: 3.9
Classifier: Programming Language :: Python :: 3.10
Classifier: Programming Language :: Python :: 3.11
Requires-Dist: click (>=8.1.7,<9.0.0)
Project-URL: Documentation, https://balouf.github.io/my-first-ph3-package
Project-URL: Repository, https://github.com/my_first_ph3_package/my-first-ph3-package
